<mon:event xmlns:mon="http://www.ibm.com/xmlns/monitoring/event/v2">
	<mon:eventPointData>
		<mon:eventData mon:eventSourceAddress="HTTP Reply.terminal.in" mon:productVersion="110010" mon:profileVersion="11">
			<mon:eventIdentity mon:eventName="HTTP Reply.InTerminal"/>
			<mon:eventSequence mon:counter="2" mon:creationTime="2021-05-06T02:19:43.285717Z"/>
			<mon:eventCorrelation mon:globalTransactionId="" mon:localTransactionId="166fd724-ae10-11eb-b35e-ac1ec9790000-1" mon:parentTransactionId=""/>
		</mon:eventData>
		<mon:messageFlowData>
			<mon:integrationServer mon:hostName="account-movements-canonical-ace-monitoringprofile-75cd54c8h9bzr" mon:name="account-movements-canonical-ace-monitoringprofile"/>
			<mon:application mon:name="AccountsCanonicalMovementsREST"/>
			<mon:messageFlow mon:name="gen.AccountsCanonicalMovementsREST" mon:threadId="359" mon:uniqueFlowName="account-movements-canonical-ace-monitoringprofile.AccountsCanonicalMovementsREST.gen.AccountsCanonicalMovementsREST"/>
			<mon:node mon:nodeLabel="HTTP Reply" mon:nodeType="ComIbmWSReplyNode" mon:terminal="in"/>
		</mon:messageFlowData>
	</mon:eventPointData>
	<mon:applicationData xmlns="">
		<mon:complexContent mon:elementName="Parameters">
			<Parameters>
				<accountNumber>7003259185</accountNumber>
				<bank>03</bank>
				<branchCode>898</branchCode>
				<currency>604</currency>
				<parent-id>7ce63d47-27ec-4c61-803c-3121d7691230</parent-id>
				<product>11</product>
				<sequenceNumber>0</sequenceNumber>
				<subProduct>205</subProduct>
				<trace-id>4bde79a30f6b46b180d1c13f60b9cef2</trace-id>
			</Parameters>
		</mon:complexContent>
	</mon:applicationData>
</mon:event>